[
{"id":"0","check-all":"店铺：","shop-name":"塬景水果旗舰店","img":"../images/cartimages/small_201507151611066434(2).jpg","scan-bigPic":"查看大图","account-for":"陕西特产 正宗洛川苹果 新鲜红富士24个80mm 脆甜多汁 产地直供","specification":"规格：默认",
"guarantee-1":"保障：","what-num":"188","del":"￥118.00","all-cart-total":"￥88.00","save-money":"save-money","promotion":"卖家促销","money":"￥188.00","collect":"收藏","del-cart":"删除"},
{"img":"../images/cartimages/small_201507151611066434(2).jpg","scan-bigPic":"查看大图","account-for":"陕西特产 正宗洛川苹果 新鲜红富士24个80mm 脆甜多汁 产地直供","specification":"规格：默认","guarantee-1":"保障：","what-num":"188","del":
"￥118.00","all-cart-total":"￥88.00","save-money":"save-money","promotion":"卖家促销","money":"￥188.00","collect":"收藏","del-cart":"删除"}
]
